[
  {
    "experiment": "passkey_retrieval",
    "method": "kivi_topk",
    "notes": "",
    "cfg.seq_len": 4096,
    "cfg.depth": 0.1,
    "cfg.K": 3072,
    "cfg.n_sink": 128,
    "cfg.n_local": 512,
    "cfg.bits": 4,
    "cfg.n_trials": 5,
    "m.accuracy": 1.0,
    "m.n_correct": 5,
    "m.n_trials": 5,
    "m.throughput_tps": 3.34859938020411
  },
  {
    "experiment": "passkey_retrieval",
    "method": "kivi_topk",
    "notes": "",
    "cfg.seq_len": 4096,
    "cfg.depth": 0.3,
    "cfg.K": 3072,
    "cfg.n_sink": 128,
    "cfg.n_local": 512,
    "cfg.bits": 4,
    "cfg.n_trials": 5,
    "m.accuracy": 1.0,
    "m.n_correct": 5,
    "m.n_trials": 5,
    "m.throughput_tps": 3.2427207110811493
  },
  {
    "experiment": "passkey_retrieval",
    "method": "kivi_topk",
    "notes": "",
    "cfg.seq_len": 4096,
    "cfg.depth": 0.5,
    "cfg.K": 3072,
    "cfg.n_sink": 128,
    "cfg.n_local": 512,
    "cfg.bits": 4,
    "cfg.n_trials": 5,
    "m.accuracy": 1.0,
    "m.n_correct": 5,
    "m.n_trials": 5,
    "m.throughput_tps": 3.229650000819982
  },
  {
    "experiment": "passkey_retrieval",
    "method": "kivi_topk",
    "notes": "",
    "cfg.seq_len": 4096,
    "cfg.depth": 0.7,
    "cfg.K": 3072,
    "cfg.n_sink": 128,
    "cfg.n_local": 512,
    "cfg.bits": 4,
    "cfg.n_trials": 5,
    "m.accuracy": 1.0,
    "m.n_correct": 5,
    "m.n_trials": 5,
    "m.throughput_tps": 3.241521288907453
  },
  {
    "experiment": "passkey_retrieval",
    "method": "kivi_topk",
    "notes": "",
    "cfg.seq_len": 4096,
    "cfg.depth": 0.9,
    "cfg.K": 3072,
    "cfg.n_sink": 128,
    "cfg.n_local": 512,
    "cfg.bits": 4,
    "cfg.n_trials": 5,
    "m.accuracy": 1.0,
    "m.n_correct": 5,
    "m.n_trials": 5,
    "m.throughput_tps": 3.292463795398903
  }
]